svcs/__init__.py
svcs/_core.py
svcs/aiohttp.py
svcs/exceptions.py
svcs/fastapi.py
svcs/flask.py
svcs/py.typed
svcs/pyramid.py
svcs/starlette.py
svcs-24.1.0.dist-info/METADATA
svcs-24.1.0.dist-info/WHEEL
svcs-24.1.0.dist-info/licenses/LICENSE
svcs-24.1.0.dist-info/RECORD
